py2ipynb2py/__init__.py
py2ipynb2py/ipytopy.py
py2ipynb2py/main.py
py2ipynb2py/pytoipy.py
py2ipynb2py-0.0.3.dist-info/LICENSE
py2ipynb2py-0.0.3.dist-info/METADATA
py2ipynb2py-0.0.3.dist-info/WHEEL
py2ipynb2py-0.0.3.dist-info/top_level.txt
py2ipynb2py-0.0.3.dist-info/RECORD
